{
	"_id" : "SR0428",
    "mainImage" : {
        "title" : {
            "EN" : "main view",
            "RU" : "main view"
        },
        "filename" : "main.jpg"
    },
    "additionalImages" : [
        {
            "title" : {
                "EN" : "Гостиная:",
                "RU" : "Гостиная:"
            },
            "filename" : "lr_1.jpg"
        },
        {
            "title" : {
                "EN" : "Гостиная:",
                "RU" : "Гостиная:"
            },
            "filename" : "lr_2.jpg"
        },
        {
            "title" : {
                "EN" : "Гостиная:",
                "RU" : "Гостиная:"
            },
            "filename" : "lr_3.jpg"
        },
        {
            "title" : {
                "EN" : "Гостиная:",
                "RU" : "Гостиная:"
            },
            "filename" : "lr_4.jpg"
        },
        {
            "title" : {
                "EN" : "Первая спальня:",
                "RU" : "Первая спальня:"
            },
            "filename" : "br1_1.jpg"
        },
        {
            "title" : {
                "EN" : "Первая спальня:",
                "RU" : "Первая спальня:"
            },
            "filename" : "br1_2.jpg"
        },
        {
            "title" : {
                "EN" : "Первая спальня:",
                "RU" : "Первая спальня:"
            },
            "filename" : "br1_3.jpg"
        },
        {
            "title" : {
                "EN" : "Первая спальня:",
                "RU" : "Первая спальня:"
            },
            "filename" : "br1_4.jpg"
        },
        {
            "title" : {
                "EN" : "Первая спальня:",
                "RU" : "Первая спальня:"
            },
            "filename" : "br1_5.jpg"
        },
        {
            "title" : {
                "EN" : "Первая спальня:",
                "RU" : "Первая спальня:"
            },
            "filename" : "br1_6.jpg"
        },
        {
            "title" : {
                "EN" : "Первая спальня:",
                "RU" : "Первая спальня:"
            },
            "filename" : "br1_7.jpg"
        },
        {
            "title" : {
                "EN" : "Вторая спальня:",
                "RU" : "Вторая спальня:"
            },
            "filename" : "br2_1.jpg"
        },
        {
            "title" : {
                "EN" : "Вторая спальня:",
                "RU" : "Вторая спальня:"
            },
            "filename" : "br2_2.jpg"
        },
        {
            "title" : {
                "EN" : "Вторая спальня:",
                "RU" : "Вторая спальня:"
            },
            "filename" : "br2_3.jpg"
        },
        {
            "title" : {
                "EN" : "Вторая спальня:",
                "RU" : "Вторая спальня:"
            },
            "filename" : "br2_4.jpg"
        },
        {
            "title" : {
                "EN" : "Кухня:",
                "RU" : "Кухня:"
            },
            "filename" : "kch_1.jpg"
        },
        {
            "title" : {
                "EN" : "Кухня:",
                "RU" : "Кухня:"
            },
            "filename" : "kch_2.jpg"
        },
        {
            "title" : {
                "EN" : "Кухня:",
                "RU" : "Кухня:"
            },
            "filename" : "kch_3.jpg"
        },
        {
            "title" : {
                "EN" : "Ванная комната:",
                "RU" : "Ванная комната:"
            },
            "filename" : "wc_1.jpg"
        },
        {
            "title" : {
                "EN" : "Ванная комната:",
                "RU" : "Ванная комната:"
            },
            "filename" : "wc_2.jpg"
        },
        {
            "title" : {
                "EN" : "Ванная комната:",
                "RU" : "Ванная комната:"
            },
            "filename" : "wc_3.jpg"
        },
        {
            "title" : {
                "EN" : "Территория:",
                "RU" : "Территория:"
            },
            "filename" : "tr_1.jpg"
        },
        {
            "title" : {
                "EN" : "Территория:",
                "RU" : "Территория:"
            },
            "filename" : "tr_2.jpg"
        },
        {
            "title" : {
                "EN" : "Территория:",
                "RU" : "Территория:"
            },
            "filename" : "tr_3.jpg"
        },
        {
            "title" : {
                "EN" : "Территория:",
                "RU" : "Территория:"
            },
            "filename" : "tr_4.jpg"
        },
        {
            "title" : {
                "EN" : "Территория:",
                "RU" : "Территория:"
            },
            "filename" : "tr_5.jpg"
        },
        {
            "title" : {
                "EN" : "Территория:",
                "RU" : "Территория:"
            },
            "filename" : "tr_6.jpg"
        }
    ],
    "title" : {
        "EN" : "Описание:",
        "RU" : "Описание:"
    },
    "briefly" : {
        "EN" : "Дом расположен в районе Мэнам на берегу сиамского залива.",
        "RU" : "Дом расположен в районе Мэнам на берегу сиамского залива."
    },
    "description" : {
        "EN" : "<p>К услугам гостей бесплатный Wi-Fi и терраса. Из окон открывается вид на океан. Дом с кондиционером состоит из 2 отдельных спален, полностью оборудованной кухни и 1 ванной комнаты. В гостиной имеется телевизор с плоским экраном и спутниковыми каналами, журнальный столик и два дивана. На кухне зоне имеется холодильник, газовая плита, микроволновая печь, чайник, тостер и обеденный стол. В первой спальне имеется двуспальная кровать, кондиционер, большой шкаф для одежды. Во второй спальне две односпальные кровати и большой шкаф для одежды. Отдельный санузел с раковиной и душем. Дом находится в 1,2 км от пирса Мэнам и в 3,3 км от курортного комплекса W Retreat Samui. Расстояние до международного аэропорта Самуи составляет 9 км.<hr></p><ul><li>Дом сдается только на короткий срок, сутки стоит 7000 бат в независимости от сезона.</li><li>Уборка каждые три дня. Интернет, вода, электричество бесплатно. Депозит не берут</li></ul> ",
        "RU" : "<p>К услугам гостей бесплатный Wi-Fi и терраса. Из окон открывается вид на океан. Дом с кондиционером состоит из 2 отдельных спален, полностью оборудованной кухни и 1 ванной комнаты. В гостиной имеется телевизор с плоским экраном и спутниковыми каналами, журнальный столик и два дивана. На кухне зоне имеется холодильник, газовая плита, микроволновая печь, чайник, тостер и обеденный стол. В первой спальне имеется двуспальная кровать, кондиционер, большой шкаф для одежды. Во второй спальне две односпальные кровати и большой шкаф для одежды. Отдельный санузел с раковиной и душем. Дом находится в 1,2 км от пирса Мэнам и в 3,3 км от курортного комплекса W Retreat Samui. Расстояние до международного аэропорта Самуи составляет 9 км.<hr></p><ul><li>Дом сдается только на короткий срок, сутки стоит 7000 бат в независимости от сезона.</li><li>Уборка каждые три дня. Интернет, вода, электричество бесплатно. Депозит не берут</li></ul> "
    },
    "type" : "house",
    "beach" : "maenam",
    "dayPrice" : 7000.0,
    "options" : {
        "conditioner" : true,
        "tv" : true,
        "washingMachine" : true,
        "dishWasher" : false,
        "hairDryer" : false,
        "microwaveOven" : true,
        "cooker" : true,
        "teaPot" : true,
        "coffeePot" : false,
        "wifi" : true,
        "internet" : true,
        "iron" : false,
        "garden" : false,
        "grill" : false,
        "swimmingPool" : false,
        "closedArea" : false,
        "seaView" : false,
        "nearSea" : false,
        "bedClothes" : true,
        "towels" : true,
        "toaster" : true,
        "babyCot" : true,
        "parking" : true,
        "terrace" : true,
        "refrigerator" : true,
        "kitchenWare" : true,
        "cleaning" : true,
        "tableWare" : true,
        "kitchen" : true,
        "jungle" : false
    },
    "sleepingRoomCount" : 2,
    "special" : false,
    "washRoomCount" : 1,
    "distanceToSea" : 0.0,
    "videoLink" : "https://youtu.be/KzPWUyPCKuw",
    "archived" : false,
    "propositionLocation" : {
        "latitude" : 0.0,
        "longitude" : 0.0
    },
    "uploadedToIk" : true,
    "_class" : "pro.nsystem.proposition.domain.localized.Proposition"
}
